Megatron-0.1.0.dist-info/METADATA
Megatron-0.1.0.dist-info/RECORD
Megatron-0.1.0.dist-info/WHEEL
Megatron-0.1.0.dist-info/top_level.txt
megatron/__init__.py
megatron/core.py
megatron/utils.py
megatron/transforms/__init__.py
megatron/transforms/common.py
megatron/transforms/image.py
megatron/transforms/numeric.py
megatron/transforms/text.py
