Metadata-Version: 2.1
Name: Megatron
Version: 0.1.0
Summary: A computation graph library for feature engineering with Numpy data
Home-page: https://github.com/ntaylorwss/megatron
Author: Nash Taylor
Author-email: nashtaylor22@gmail.com
License: MIT
Download-URL: https://github.com/ntaylorwss/megatron/archive/master.zip
Platform: UNKNOWN
Classifier: Programming Language :: Python :: 3
Classifier: License :: OSI Approved :: MIT License
Classifier: Operating System :: OS Independent
